{
  "general": [
    {
      "equipo": "VILLA LURO NORTE",
      "pj": 35,
      "g": 31,
      "e": 0,
      "p": 4,
      "pts": 97
    },
    {
      "equipo": "LOS CUERVOS",
      "pj": 35,
      "g": 28,
      "e": 3,
      "p": 4,
      "pts": 94
    },
    {
      "equipo": "ESTRELLA DE BOEDO",
      "pj": 35,
      "g": 27,
      "e": 2,
      "p": 6,
      "pts": 91
    },
    {
      "equipo": "PLATENSE BLANCO",
      "pj": 35,
      "g": 26,
      "e": 2,
      "p": 7,
      "pts": 89
    },
    {
      "equipo": "C. A. VIRGEN DEL CARMEN",
      "pj": 35,
      "g": 21,
      "e": 4,
      "p": 10,
      "pts": 81
    },
    {
      "equipo": "CLUB LA PATERNAL",
      "pj": 40,
      "g": 18,
      "e": 4,
      "p": 18,
      "pts": 80
    },
    {
      "equipo": "A. A. A. J.",
      "pj": 35,
      "g": 22,
      "e": 0,
      "p": 13,
      "pts": 79
    },
    {
      "equipo": "FLORES CLUB",
      "pj": 40,
      "g": 17,
      "e": 5,
      "p": 15,
      "pts": 76
    },
    {
      "equipo": "CLUB AT. LUGANO",
      "pj": 35,
      "g": 18,
      "e": 3,
      "p": 14,
      "pts": 74
    },
    {
      "equipo": "LOS ALBOS",
      "pj": 40,
      "g": 16,
      "e": 2,
      "p": 19,
      "pts": 71
    },
    {
      "equipo": "NUEVA CHICAGO",
      "pj": 40,
      "g": 14,
      "e": 3,
      "p": 23,
      "pts": 71
    },
    {
      "equipo": "C. S. y D. PAMPERO",
      "pj": 40,
      "g": 12,
      "e": 2,
      "p": 26,
      "pts": 66
    },
    {
      "equipo": "CLUB PACIFICO",
      "pj": 35,
      "g": 12,
      "e": 4,
      "p": 19,
      "pts": 63
    },
    {
      "equipo": "VILLA HERMINIA",
      "pj": 40,
      "g": 11,
      "e": 0,
      "p": 26,
      "pts": 59
    },
    {
      "equipo": "EST. PORTEÑO ROJO",
      "pj": 35,
      "g": 4,
      "e": 0,
      "p": 23,
      "pts": 35
    },
    {
      "equipo": "SANELI F.C.",
      "pj": 35,
      "g": 1,
      "e": 0,
      "p": 32,
      "pts": 35
    }
  ],
  "categorias": {
    "2013": [
      {
        "equipo": "CLUB LA PATERNAL",
        "pj": 8,
        "g": 7,
        "e": 1,
        "p": 0,
        "pts": 23
      },
      {
        "equipo": "VILLA LURO NORTE",
        "pj": 7,
        "g": 7,
        "e": 0,
        "p": 0,
        "pts": 21
      },
      {
        "equipo": "LOS CUERVOS",
        "pj": 7,
        "g": 6,
        "e": 1,
        "p": 0,
        "pts": 20
      },
      {
        "equipo": "ESTRELLA DE BOEDO",
        "pj": 7,
        "g": 5,
        "e": 1,
        "p": 1,
        "pts": 18
      },
      {
        "equipo": "CLUB AT. LUGANO",
        "pj": 7,
        "g": 5,
        "e": 0,
        "p": 2,
        "pts": 17
      },
      {
        "equipo": "LOS ALBOS",
        "pj": 8,
        "g": 4,
        "e": 1,
        "p": 3,
        "pts": 17
      },
      {
        "equipo": "PLATENSE BLANCO",
        "pj": 7,
        "g": 4,
        "e": 1,
        "p": 2,
        "pts": 16
      },
      {
        "equipo": "A. A. A. J.",
        "pj": 7,
        "g": 4,
        "e": 0,
        "p": 3,
        "pts": 15
      },
      {
        "equipo": "C. A. VIRGEN DEL CARMEN",
        "pj": 7,
        "g": 4,
        "e": 0,
        "p": 3,
        "pts": 15
      },
      {
        "equipo": "CLUB PACIFICO",
        "pj": 7,
        "g": 3,
        "e": 1,
        "p": 3,
        "pts": 14
      },
      {
        "equipo": "C. S. y D. PAMPERO",
        "pj": 8,
        "g": 3,
        "e": 0,
        "p": 5,
        "pts": 14
      },
      {
        "equipo": "VILLA HERMINIA",
        "pj": 8,
        "g": 2,
        "e": 0,
        "p": 6,
        "pts": 12
      },
      {
        "equipo": "NUEVA CHICAGO",
        "pj": 8,
        "g": 1,
        "e": 0,
        "p": 7,
        "pts": 10
      },
      {
        "equipo": "FLORES CLUB",
        "pj": 8,
        "g": 1,
        "e": 0,
        "p": 4,
        "pts": 7
      },
      {
        "equipo": "SANELI F.C.",
        "pj": 7,
        "g": 0,
        "e": 0,
        "p": 6,
        "pts": 6
      },
      {
        "equipo": "EST. PORTEÑO ROJO",
        "pj": 7,
        "g": 0,
        "e": 0,
        "p": 0,
        "pts": 0
      }
    ],
    "2014/15": [
      {
        "equipo": "C. A. VIRGEN DEL CARMEN",
        "pj": 7,
        "g": 6,
        "e": 1,
        "p": 0,
        "pts": 20
      },
      {
        "equipo": "PLATENSE BLANCO",
        "pj": 7,
        "g": 6,
        "e": 0,
        "p": 1,
        "pts": 19
      },
      {
        "equipo": "ESTRELLA DE BOEDO",
        "pj": 7,
        "g": 6,
        "e": 0,
        "p": 1,
        "pts": 19
      },
      {
        "equipo": "VILLA HERMINIA",
        "pj": 8,
        "g": 5,
        "e": 0,
        "p": 3,
        "pts": 18
      },
      {
        "equipo": "LOS CUERVOS",
        "pj": 7,
        "g": 5,
        "e": 1,
        "p": 1,
        "pts": 18
      },
      {
        "equipo": "FLORES CLUB",
        "pj": 8,
        "g": 4,
        "e": 1,
        "p": 3,
        "pts": 17
      },
      {
        "equipo": "LOS ALBOS",
        "pj": 8,
        "g": 4,
        "e": 0,
        "p": 4,
        "pts": 16
      },
      {
        "equipo": "CLUB PACIFICO",
        "pj": 7,
        "g": 4,
        "e": 0,
        "p": 3,
        "pts": 15
      },
      {
        "equipo": "CLUB AT. LUGANO",
        "pj": 7,
        "g": 4,
        "e": 0,
        "p": 3,
        "pts": 15
      },
      {
        "equipo": "VILLA LURO NORTE",
        "pj": 7,
        "g": 3,
        "e": 0,
        "p": 4,
        "pts": 13
      },
      {
        "equipo": "A. A. A. J.",
        "pj": 7,
        "g": 3,
        "e": 0,
        "p": 4,
        "pts": 13
      },
      {
        "equipo": "CLUB LA PATERNAL",
        "pj": 8,
        "g": 2,
        "e": 1,
        "p": 5,
        "pts": 13
      },
      {
        "equipo": "NUEVA CHICAGO",
        "pj": 8,
        "g": 2,
        "e": 1,
        "p": 5,
        "pts": 13
      },
      {
        "equipo": "C. S. y D. PAMPERO",
        "pj": 8,
        "g": 1,
        "e": 1,
        "p": 6,
        "pts": 11
      },
      {
        "equipo": "EST. PORTEÑO ROJO",
        "pj": 7,
        "g": 1,
        "e": 0,
        "p": 6,
        "pts": 9
      },
      {
        "equipo": "SANELI F.C.",
        "pj": 7,
        "g": 0,
        "e": 0,
        "p": 7,
        "pts": 7
      }
    ],
    "2016/17": [
      {
        "equipo": "VILLA LURO NORTE",
        "pj": 7,
        "g": 7,
        "e": 0,
        "p": 0,
        "pts": 21
      },
      {
        "equipo": "ESTRELLA DE BOEDO",
        "pj": 7,
        "g": 7,
        "e": 0,
        "p": 0,
        "pts": 21
      },
      {
        "equipo": "LOS CUERVOS",
        "pj": 7,
        "g": 7,
        "e": 0,
        "p": 0,
        "pts": 21
      },
      {
        "equipo": "C. S. y D. PAMPERO",
        "pj": 8,
        "g": 5,
        "e": 0,
        "p": 3,
        "pts": 18
      },
      {
        "equipo": "PLATENSE BLANCO",
        "pj": 7,
        "g": 5,
        "e": 0,
        "p": 2,
        "pts": 17
      },
      {
        "equipo": "FLORES CLUB",
        "pj": 8,
        "g": 4,
        "e": 1,
        "p": 3,
        "pts": 17
      },
      {
        "equipo": "LOS ALBOS",
        "pj": 8,
        "g": 4,
        "e": 0,
        "p": 4,
        "pts": 16
      },
      {
        "equipo": "C. A. VIRGEN DEL CARMEN",
        "pj": 7,
        "g": 4,
        "e": 1,
        "p": 2,
        "pts": 16
      },
      {
        "equipo": "A. A. A. J.",
        "pj": 7,
        "g": 4,
        "e": 0,
        "p": 3,
        "pts": 15
      },
      {
        "equipo": "CLUB AT. LUGANO",
        "pj": 7,
        "g": 2,
        "e": 1,
        "p": 4,
        "pts": 12
      },
      {
        "equipo": "NUEVA CHICAGO",
        "pj": 8,
        "g": 2,
        "e": 0,
        "p": 6,
        "pts": 12
      },
      {
        "equipo": "VILLA HERMINIA",
        "pj": 8,
        "g": 2,
        "e": 0,
        "p": 5,
        "pts": 11
      },
      {
        "equipo": "EST. PORTEÑO ROJO",
        "pj": 7,
        "g": 2,
        "e": 0,
        "p": 5,
        "pts": 11
      },
      {
        "equipo": "CLUB PACIFICO",
        "pj": 7,
        "g": 1,
        "e": 1,
        "p": 5,
        "pts": 10
      },
      {
        "equipo": "CLUB LA PATERNAL",
        "pj": 8,
        "g": 0,
        "e": 2,
        "p": 6,
        "pts": 10
      },
      {
        "equipo": "SANELI F.C.",
        "pj": 7,
        "g": 0,
        "e": 0,
        "p": 7,
        "pts": 7
      }
    ],
    "2018/19": [
      {
        "equipo": "VILLA LURO NORTE",
        "pj": 7,
        "g": 7,
        "e": 0,
        "p": 0,
        "pts": 21
      },
      {
        "equipo": "A. A. A. J.",
        "pj": 7,
        "g": 7,
        "e": 0,
        "p": 0,
        "pts": 21
      },
      {
        "equipo": "FLORES CLUB",
        "pj": 8,
        "g": 6,
        "e": 1,
        "p": 1,
        "pts": 21
      },
      {
        "equipo": "PLATENSE BLANCO",
        "pj": 7,
        "g": 6,
        "e": 0,
        "p": 1,
        "pts": 19
      },
      {
        "equipo": "C. A. VIRGEN DEL CARMEN",
        "pj": 7,
        "g": 5,
        "e": 2,
        "p": 0,
        "pts": 19
      },
      {
        "equipo": "NUEVA CHICAGO",
        "pj": 8,
        "g": 5,
        "e": 1,
        "p": 2,
        "pts": 19
      },
      {
        "equipo": "LOS CUERVOS",
        "pj": 7,
        "g": 4,
        "e": 1,
        "p": 2,
        "pts": 16
      },
      {
        "equipo": "ESTRELLA DE BOEDO",
        "pj": 7,
        "g": 3,
        "e": 1,
        "p": 3,
        "pts": 14
      },
      {
        "equipo": "CLUB AT. LUGANO",
        "pj": 7,
        "g": 3,
        "e": 0,
        "p": 4,
        "pts": 13
      },
      {
        "equipo": "LOS ALBOS",
        "pj": 8,
        "g": 3,
        "e": 0,
        "p": 3,
        "pts": 12
      },
      {
        "equipo": "CLUB LA PATERNAL",
        "pj": 8,
        "g": 2,
        "e": 0,
        "p": 6,
        "pts": 12
      },
      {
        "equipo": "CLUB PACIFICO",
        "pj": 7,
        "g": 2,
        "e": 0,
        "p": 5,
        "pts": 11
      },
      {
        "equipo": "C. S. y D. PAMPERO",
        "pj": 8,
        "g": 1,
        "e": 0,
        "p": 7,
        "pts": 10
      },
      {
        "equipo": "EST. PORTEÑO ROJO",
        "pj": 7,
        "g": 1,
        "e": 0,
        "p": 6,
        "pts": 9
      },
      {
        "equipo": "SANELI F.C.",
        "pj": 7,
        "g": 1,
        "e": 0,
        "p": 6,
        "pts": 9
      },
      {
        "equipo": "VILLA HERMINIA",
        "pj": 8,
        "g": 0,
        "e": 0,
        "p": 7,
        "pts": 7
      }
    ],
    "2020/21/22": [
      {
        "equipo": "CLUB LA PATERNAL",
        "pj": 8,
        "g": 7,
        "e": 0,
        "p": 1,
        "pts": 22
      },
      {
        "equipo": "VILLA LURO NORTE",
        "pj": 7,
        "g": 7,
        "e": 0,
        "p": 0,
        "pts": 21
      },
      {
        "equipo": "ESTRELLA DE BOEDO",
        "pj": 7,
        "g": 6,
        "e": 0,
        "p": 1,
        "pts": 19
      },
      {
        "equipo": "LOS CUERVOS",
        "pj": 7,
        "g": 6,
        "e": 0,
        "p": 1,
        "pts": 19
      },
      {
        "equipo": "PLATENSE BLANCO",
        "pj": 7,
        "g": 5,
        "e": 1,
        "p": 1,
        "pts": 18
      },
      {
        "equipo": "CLUB AT. LUGANO",
        "pj": 7,
        "g": 4,
        "e": 2,
        "p": 1,
        "pts": 17
      },
      {
        "equipo": "NUEVA CHICAGO",
        "pj": 8,
        "g": 4,
        "e": 1,
        "p": 3,
        "pts": 17
      },
      {
        "equipo": "A. A. A. J.",
        "pj": 7,
        "g": 4,
        "e": 0,
        "p": 3,
        "pts": 15
      },
      {
        "equipo": "FLORES CLUB",
        "pj": 8,
        "g": 2,
        "e": 2,
        "p": 4,
        "pts": 14
      },
      {
        "equipo": "CLUB PACIFICO",
        "pj": 7,
        "g": 2,
        "e": 2,
        "p": 3,
        "pts": 13
      },
      {
        "equipo": "C. S. y D. PAMPERO",
        "pj": 8,
        "g": 2,
        "e": 1,
        "p": 5,
        "pts": 13
      },
      {
        "equipo": "VILLA HERMINIA",
        "pj": 8,
        "g": 2,
        "e": 0,
        "p": 5,
        "pts": 11
      },
      {
        "equipo": "C. A. VIRGEN DEL CARMEN",
        "pj": 7,
        "g": 2,
        "e": 0,
        "p": 5,
        "pts": 11
      },
      {
        "equipo": "LOS ALBOS",
        "pj": 8,
        "g": 1,
        "e": 1,
        "p": 5,
        "pts": 10
      },
      {
        "equipo": "EST. PORTEÑO ROJO",
        "pj": 7,
        "g": 0,
        "e": 0,
        "p": 6,
        "pts": 6
      },
      {
        "equipo": "SANELI F.C.",
        "pj": 7,
        "g": 0,
        "e": 0,
        "p": 6,
        "pts": 6
      }
    ]
  }
}